plare/__init__.py
plare/exception.py
plare/lexer.py
plare/parser.py
plare/py.typed
plare/token.py
plare/utils.py
plare-1.5.0.dist-info/METADATA
plare-1.5.0.dist-info/WHEEL
plare-1.5.0.dist-info/licenses/LICENSE
plare-1.5.0.dist-info/RECORD
