Metadata-Version: 2.3
Name: plare
Version: 1.5.0
Summary: Language description language, Lexer, and Parser for Python3
Project-URL: Homepage, https://github.com/sambyeol/plare
Project-URL: Bug Tracker, https://github.com/sambyeol/plare/issues
Author-email: Seokhyun Lee <gbvrcx@gmail.com>
Classifier: Operating System :: OS Independent
Classifier: Programming Language :: Python :: 3
Classifier: Programming Language :: Python :: 3 :: Only
Classifier: Programming Language :: Python :: 3.12
Classifier: Programming Language :: Python :: 3.13
Classifier: Typing :: Typed
Requires-Python: >=3.12
Requires-Dist: rich>=13
Provides-Extra: dev
Requires-Dist: black>=23; extra == 'dev'
Requires-Dist: isort>=5; extra == 'dev'
Provides-Extra: test
Requires-Dist: pytest>=7; extra == 'test'
Provides-Extra: type
Requires-Dist: pyright>=1.1; extra == 'type'
